setup.cfg
setup.py
trakio/__init__.py
trakio/client.py
trakio/exceptions.py
trakio.egg-info/PKG-INFO
trakio.egg-info/SOURCES.txt
trakio.egg-info/dependency_links.txt
trakio.egg-info/entry_points.txt
trakio.egg-info/not-zip-safe
trakio.egg-info/requires.txt
trakio.egg-info/top_level.txt