Metadata-Version: 1.0
Name: trakio
Version: 1.0.0dev
Summary: Client library for accessing the trak.io API.
Home-page: https://github.com/userapp-io/trakio-python/
Author: Robin Orheden
Author-email: robin.orheden@userapp.io
License: MIT
Keywords: user analytics,user engagement,trak.io
Platform: UNKNOWN
